{
  "type": "crafting_shapeless",
  "category": "equipment",
  "ingredients": [
    {
      "item": "netherite_axe"
    },
    {
      "item": "netherite_pickaxe"
    },
    {
      "item": "netherite_hoe"
    },
    {
      "item": "netherite_shovel"
    }
  ],
  "result": {
    "count": 1,
    "id": "netherite_axe",
    "components": {
      "lore":["{\"color\":\"aqua\",\"italic\":false,\"text\":\"🔨\"}"],
      "custom_data": {
        "jkmt": [
          "netherite"
        ]
      },
      "max_damage": 8124,
      "tool": {
        "rules": [
          {
            "blocks": "#jkmt:diamond",
            "speed": 9,
            "correct_for_drops": true
          }
        ]
      }
    }
  }
}